ocrd_calamari/__init__.py
ocrd_calamari/cli.py
ocrd_calamari/config.py
ocrd_calamari/ocrd-tool.json
ocrd_calamari/recognize.py
test/assets/__init__.py
test/assets/param-binarize-invalid.json
test/assets/param-binarize.json
ocrd_calamari-1.0.6.dist-info/LICENSE
ocrd_calamari-1.0.6.dist-info/METADATA
ocrd_calamari-1.0.6.dist-info/WHEEL
ocrd_calamari-1.0.6.dist-info/entry_points.txt
ocrd_calamari-1.0.6.dist-info/top_level.txt
ocrd_calamari-1.0.6.dist-info/RECORD
