Metadata-Version: 2.1
Name: ocrd-calamari
Version: 1.0.6
Summary: Calamari bindings
Home-page: https://github.com/OCR-D/ocrd_calamari
Author: Konstantin Baierer, Mike Gerber
Author-email: unixprog@gmail.com, mike.gerber@sbb.spk-berlin.de
License: Apache License 2.0
Platform: UNKNOWN
License-File: LICENSE
Requires-Dist: tensorflow (>=2.5.0)
Requires-Dist: numpy (<1.24.0)
Requires-Dist: protobuf (<4.0)
Requires-Dist: calamari-ocr (==1.0.*)
Requires-Dist: setuptools (>=41.0.0)
Requires-Dist: click
Requires-Dist: ocrd (>=2.22.0)
